main.py
source_rss/__init__.py
source_rss/components.py
source_rss/manifest.yaml
source_rss/run.py
source_rss/source.py
airbyte_source_rss-1.0.31.dist-info/METADATA
airbyte_source_rss-1.0.31.dist-info/WHEEL
airbyte_source_rss-1.0.31.dist-info/entry_points.txt
airbyte_source_rss-1.0.31.dist-info/RECORD
