Metadata-Version: 2.3
Name: airbyte-source-rss
Version: 1.0.31
Summary: Source implementation for rss.
License: MIT
Author: Airbyte
Author-email: contact@airbyte.io
Requires-Python: >=3.9,<3.12
Classifier: License :: OSI Approved :: MIT License
Classifier: Programming Language :: Python :: 3
Classifier: Programming Language :: Python :: 3.9
Classifier: Programming Language :: Python :: 3.10
Classifier: Programming Language :: Python :: 3.11
Requires-Dist: airbyte-cdk (>=0,<1)
Requires-Dist: feedparser (==6.0.10)
Requires-Dist: pytz (==2022.6)
Project-URL: Documentation, https://docs.airbyte.com/integrations/sources/rss
Project-URL: Homepage, https://airbyte.com
Project-URL: Repository, https://github.com/airbytehq/airbyte
